{
    "types": [
        {
            "id": 0,
            "name": "test",
            "sprites": [
                "sprites/bloc0.png",
                "sprites/bloc1.png"
            ],
            "solid": true,
            "behaviour": {
                "liste": []
            }
        },
        {
            "id": 1,
            "name": "test2",
            "sprites": [
                "sprites/bloc2.png"
            ],
            "solid": false,
            "behaviour": {
                "liste": [
                    "IncreaseSpeedOnTouch",
                    "BreakOnTouch"
                ],
                "IncreaseSpeedOnTouch": 1
            }
        },
        {
            "id": 2,
            "name": "invisible",
            "sprites": [
                "sprites/bloc1.png"
            ],
            "solid": false,
            "behaviour": {
                "IncreaseSpeedOnTouch": "1",
                "liste": [
                    "BreakOnTouch",
                    "IncreaseSpeedOnTouch"
                ]
            }
        }
    ]
}